bulk_translate/__init__.py
bulk_translate/api.py
bulk_translate/translate.py
bulk_translate/src/__init__.py
bulk_translate/src/service_args.py
bulk_translate/src/service_dynamic.py
bulk_translate/src/service_prompt.py
bulk_translate/src/span.py
bulk_translate/src/spans_parser.py
bulk_translate/src/utils.py
bulk_translate/src/pipeline/__init__.py
bulk_translate/src/pipeline/context.py
bulk_translate/src/pipeline/launcher.py
bulk_translate/src/pipeline/translator.py
bulk_translate/src/pipeline/utils.py
bulk_translate/src/pipeline/items/__init__.py
bulk_translate/src/pipeline/items/base.py
bulk_translate/src/pipeline/items/map.py
bulk_translate-0.25.2.dist-info/LICENSE
bulk_translate-0.25.2.dist-info/METADATA
bulk_translate-0.25.2.dist-info/WHEEL
bulk_translate-0.25.2.dist-info/top_level.txt
bulk_translate-0.25.2.dist-info/RECORD
