Metadata-Version: 2.1
Name: bulk_translate
Version: 0.25.2
Summary: A tiny Python no-string package for performing translation of a massive CSV/JSONL files with optionally pre-annotated object spans
Home-page: https://github.com/nicolay-r/bulk-translate
Author: Nicolay Rusnachenko
Author-email: rusnicolay@gmail.com
License: MIT License
Keywords: natural language processing,machine translation,translation
Classifier: Programming Language :: Python
Classifier: Programming Language :: Python :: 3.9
Classifier: Topic :: Software Development :: Libraries :: Python Modules
Classifier: Topic :: Scientific/Engineering :: Information Analysis
Classifier: Topic :: Text Processing :: Linguistic
Requires-Python: >=3.6
License-File: LICENSE
